README.md
setup.cfg
setup.py
NOOR/__init__.py
NOOR/topsis.py
Topsis_Noor_101903591.egg-info/PKG-INFO
Topsis_Noor_101903591.egg-info/SOURCES.txt
Topsis_Noor_101903591.egg-info/dependency_links.txt
Topsis_Noor_101903591.egg-info/top_level.txt